bareclient/__init__.py
bareclient/acgi/README.md
bareclient/acgi/__init__.py
bareclient/acgi/asyncio_events.py
bareclient/acgi/connector.py
bareclient/acgi/h11_protocol.py
bareclient/acgi/h2_protocol.py
bareclient/acgi/http_protocol.py
bareclient/acgi/requester.py
bareclient/acgi/types.py
bareclient/acgi/utils.py
bareclient/client.py
bareclient/constants.py
bareclient/helpers.py
bareclient/middleware.py
bareclient/middlewares/__init__.py
bareclient/middlewares/basic_authorization.py
bareclient/middlewares/compression.py
bareclient/middlewares/session.py
bareclient/py.typed
bareclient/request.py
bareclient/response.py
bareclient/ssl_contexts.py
bareclient-5.0.1.dist-info/LICENSE
bareclient-5.0.1.dist-info/WHEEL
bareclient-5.0.1.dist-info/METADATA
bareclient-5.0.1.dist-info/RECORD
