Metadata-Version: 2.1
Name: bareclient
Version: 5.0.1
Summary: A lightweight asyncio HTTP client
Home-page: https://github.com/rob-blackbourn/bareClient
License: Apache-2.0
Author: Rob Blackbourn
Author-email: rob.blackbourn@gmail.com
Requires-Python: >=3.7,<4.0
Classifier: License :: OSI Approved :: Apache Software License
Classifier: Programming Language :: Python :: 3
Classifier: Programming Language :: Python :: 3.7
Classifier: Programming Language :: Python :: 3.8
Classifier: Programming Language :: Python :: 3.9
Requires-Dist: bareutils (>=4.0.0,<5.0.0)
Requires-Dist: h11 (>=0.12.0,<0.13.0)
Requires-Dist: h2 (>=4.0,<5.0)
Project-URL: Repository, https://github.com/rob-blackbourn/bareClient
